test_package/__init__.py
test_package/heatcapacity.py
CM2CALPHAD-0.1.0.dist-info/LICENSE
CM2CALPHAD-0.1.0.dist-info/METADATA
CM2CALPHAD-0.1.0.dist-info/WHEEL
CM2CALPHAD-0.1.0.dist-info/top_level.txt
CM2CALPHAD-0.1.0.dist-info/RECORD
