Metadata-Version: 2.1
Name: CM2CALPHAD
Version: 0.1.0
Summary: Computational Methods to CALPHAD
Home-page: https://CM2CALPHAD.readthedocs.io/
Author: Javier Jofre
Author-email: javier.jofre@polymtl.ca
License: GPLv3
Classifier: Intended Audience :: Developers
Classifier: License :: OSI Approved :: GNU Affero General Public License v3
Classifier: Programming Language :: Python
Classifier: Programming Language :: Python :: 3
Classifier: Programming Language :: Python :: 3.6
Classifier: Programming Language :: Python :: 3.7
Classifier: Programming Language :: Python :: 3.8
Classifier: Programming Language :: Python :: 3.9
Classifier: Operating System :: OS Independent
License-File: LICENSE
Requires-Dist: numpy
